pdf_tables_to_excel/__init__.py
pdf_tables_to_excel/api.py
pdf_tables_to_excel/cli.py
pdf_tables_to_excel/docling_backend.py
pdf_tables_to_excel/excel_writer.py
pdf_tables_to_excel-0.1.0.dist-info/licenses/LICENSE
pdf_tables_to_excel-0.1.0.dist-info/METADATA
pdf_tables_to_excel-0.1.0.dist-info/WHEEL
pdf_tables_to_excel-0.1.0.dist-info/entry_points.txt
pdf_tables_to_excel-0.1.0.dist-info/top_level.txt
pdf_tables_to_excel-0.1.0.dist-info/RECORD
