Metadata-Version: 2.4
Name: pdf-tables-to-excel
Version: 0.1.0
Summary: Extract tables from PDFs using Docling and export them into nicely formatted Excel workbooks.
Author-email: Your Name <you@example.com>
License: MIT License
Project-URL: Homepage, https://github.com/yourname/pdf-tables-to-excel
Project-URL: Source, https://github.com/yourname/pdf-tables-to-excel
Project-URL: Issues, https://github.com/yourname/pdf-tables-to-excel/issues
Classifier: Programming Language :: Python
Classifier: Programming Language :: Python :: 3
Classifier: Programming Language :: Python :: 3.9
Classifier: Programming Language :: Python :: 3.10
Classifier: Programming Language :: Python :: 3.11
Classifier: License :: OSI Approved :: MIT License
Classifier: Operating System :: OS Independent
Classifier: Intended Audience :: Developers
Classifier: Intended Audience :: Financial and Insurance Industry
Classifier: Topic :: Office/Business :: Financial
Classifier: Topic :: Text Processing :: Markup :: LaTeX
Classifier: Topic :: Utilities
Requires-Python: >=3.9
License-File: LICENSE
Requires-Dist: docling>=2.6.0
Requires-Dist: pandas>=2.0.0
Requires-Dist: xlsxwriter>=3.0.0
Dynamic: license-file
